{
  "project_info": {
    "project_number": "404610310159",
    "project_id": "service-yuk",
    "storage_bucket": "service-yuk.appspot.com"
  },
  "client": [
    {
      "client_info": {
        "mobilesdk_app_id": "1:404610310159:android:7d261721d7b6a8e5d8437a",
        "android_client_info": {
          "package_name": "com.example.service_yuk"
        }
      },
      "oauth_client": [],
      "api_key": [
        {
          "current_key": "AIzaSyBcrHraS2mSwW3Ur1WyCzz50FafvuW1pTg"
        }
      ],
      "services": {
        "appinvite_service": {
          "other_platform_oauth_client": []
        }
      }
    }
  ],
  "configuration_version": "1"
}